.gitattributes
.gitignore
LICENSE
Machine Learning for Pose Estimation using SLEAP.pptx
README.md
cfr_header_output.mp4
environment.yml
exact_cfr_output.mp4
final_cfr_output.mp4
new_cfr_output.mp4
output.mp4
pyproject.toml
trajpred.slp
autosleap/__init__.py
autosleap/autoanalysis.py
autosleap/cli_parser.py
autosleap/files.py
autosleap/metadata.py
autosleap/trajectory.py
autosleap/video.py
autosleap/visualize.py
autosleap.egg-info/PKG-INFO
autosleap.egg-info/SOURCES.txt
autosleap.egg-info/dependency_links.txt
autosleap.egg-info/entry_points.txt
autosleap.egg-info/requires.txt
autosleap.egg-info/top_level.txt
autosleap/assets/icon.svg
autosleap/assets/icon128.png
autosleap/assets/icon16.png
autosleap/assets/icon32.png
autosleap/assets/icon64.png
autosleap/assets/icon_active.svg
autosleap/assets/icon_active128.png
autosleap/assets/icon_idle.svg
autosleap/assets/icon_idle128.png
autosleap/gui/__init__.py
autosleap/gui/app.py
autosleap/gui/view.py
autosleap/gui/widgets.py
autosleap/process/__init__.py
autosleap/process/common.py
autosleap/process/jobs.py